fury/__init__.py
fury/__init__.pyi
fury/_version.py
fury/actor.py
fury/colormap.py
fury/convert.py
fury/decorators.py
fury/deprecator.py
fury/gltf.py
fury/interactor.py
fury/io.py
fury/layout.py
fury/lib.py
fury/material.py
fury/molecular.py
fury/optpkg.py
fury/pick.py
fury/pkg_info.py
fury/primitive.py
fury/py.typed
fury/testing.py
fury/transform.py
fury/utils.py
fury/window.py
fury/actors/__init__.py
fury/actors/__init__.pyi
fury/actors/odf_slicer.py
fury/actors/peak.py
fury/actors/tensor.py
fury/actors/tests/__init__.py
fury/actors/tests/test_peak.py
fury/animation/__init__.py
fury/animation/__init__.pyi
fury/animation/animation.py
fury/animation/helpers.py
fury/animation/interpolator.py
fury/animation/timeline.py
fury/animation/tests/__init__.py
fury/animation/tests/test_animation.py
fury/animation/tests/test_helpers.py
fury/animation/tests/test_interpolators.py
fury/animation/tests/test_timeline.py
fury/data/__init__.py
fury/data/__init__.pyi
fury/data/fetcher.py
fury/data/files/KhronosGltfSamples.json
fury/data/files/dipy_colormaps.json
fury/data/files/evenly_distributed_sphere_362.npz
fury/data/files/evenly_distributed_sphere_642.npz
fury/data/files/evenly_distributed_sphere_724.npz
fury/data/files/repulsion100.npz
fury/data/files/repulsion200.npz
fury/data/files/repulsion724.npz
fury/data/files/selector_actors.log.gz
fury/data/files/selector_faces.log.gz
fury/data/files/selector_vertices.log.gz
fury/data/files/test_button_and_slider_widgets.log.gz
fury/data/files/test_card_ui.json
fury/data/files/test_card_ui.log.gz
fury/data/files/test_custom_interactor_style_events.log.gz
fury/data/files/test_double_click_events.log.gz
fury/data/files/test_grid_ui.json
fury/data/files/test_grid_ui.log.gz
fury/data/files/test_playback_panel.json
fury/data/files/test_playback_panel.log.gz
fury/data/files/test_ui_button_panel.json
fury/data/files/test_ui_button_panel.log.gz
fury/data/files/test_ui_checkbox_default.json
fury/data/files/test_ui_checkbox_default.log.gz
fury-0.11.0.dist-info/METADATA
fury-0.11.0.dist-info/WHEEL
fury-0.11.0.dist-info/licenses/AUTHORS.rst
fury-0.11.0.dist-info/licenses/LICENSE
fury-0.11.0.dist-info/RECORD
