Metadata-Version: 2.3
Name: fury
Version: 0.11.0
Summary: FURY - Free Unified Rendering in pYthon. A free and open-source software library for Scientific Visualization and 3D animations
Project-URL: Documentation, https://fury.gl
Project-URL: Source, https://github.com/fury-gl/fury
Project-URL: Tracker, https://github.com/fury-gl/fury/issues
Author-email: Eleftherios Garyfallidis <fury@python.org>, Serge Koudoro <fury@python.org>, Javier Guaje <fury@python.org>, Marc-Alexandre Côté <fury@python.org>, Soham Biswas <fury@python.org>, David Reagan <fury@python.org>, Nasim Anousheh <fury@python.org>, Filipi Silva <fury@python.org>, Geoffrey Fox <fury@python.org>
Maintainer-email: FURY Developers <fury@python.org>
License: Copyright (c) 2024, FURY - Free Unified Rendering in Python. All rights reserved.
License-File: AUTHORS.rst
License-File: LICENSE
Keywords: 3D,3D rendering,Physically based rendering,Scientific Visualization,animation,networks,physics,physics engine,shaders,simulation,visualization
Classifier: Development Status :: 4 - Beta
Classifier: Environment :: Console
Classifier: Intended Audience :: Science/Research
Classifier: License :: OSI Approved :: MIT License
Classifier: Natural Language :: English
Classifier: Operating System :: OS Independent
Classifier: Programming Language :: Python
Classifier: Programming Language :: Python :: 3.8
Classifier: Programming Language :: Python :: 3.9
Classifier: Programming Language :: Python :: 3.10
Classifier: Programming Language :: Python :: 3.11
Classifier: Topic :: Scientific/Engineering
Requires-Python: >=3.8
Requires-Dist: aiohttp>=3.8.4
Requires-Dist: lazy-loader>=0.4
Requires-Dist: numpy>=1.15
Requires-Dist: packaging>=17.0
Requires-Dist: pillow>=5.4.1
Requires-Dist: pygltflib>=1.15.3
Requires-Dist: scipy>=1.0
Requires-Dist: vtk>=9.1.0
Provides-Extra: all
Requires-Dist: coverage; extra == 'all'
Requires-Dist: data-science-types; extra == 'all'
Requires-Dist: dipy; extra == 'all'
Requires-Dist: gitpython; extra == 'all'
Requires-Dist: matplotlib>=1.5.3; extra == 'all'
Requires-Dist: mypy; extra == 'all'
Requires-Dist: nibabel; extra == 'all'
Requires-Dist: numpydoc; extra == 'all'
Requires-Dist: pre-commit; extra == 'all'
Requires-Dist: pytest!=5.3.4; extra == 'all'
Requires-Dist: pytest-cov; extra == 'all'
Requires-Dist: pytest-doctestplus; extra == 'all'
Requires-Dist: ruff; extra == 'all'
Requires-Dist: sphinx>=6.1.2; extra == 'all'
Requires-Dist: texext; extra == 'all'
Requires-Dist: tomli; (python_version < '3.11') and extra == 'all'
Requires-Dist: twine; extra == 'all'
Requires-Dist: types-pillow; extra == 'all'
Provides-Extra: dev
Requires-Dist: gitpython; extra == 'dev'
Requires-Dist: twine; extra == 'dev'
Provides-Extra: doc
Requires-Dist: matplotlib>=1.5.3; extra == 'doc'
Requires-Dist: numpydoc; extra == 'doc'
Requires-Dist: sphinx>=6.1.2; extra == 'doc'
Requires-Dist: texext; extra == 'doc'
Requires-Dist: tomli; (python_version < '3.11') and extra == 'doc'
Provides-Extra: medical
Requires-Dist: dipy; extra == 'medical'
Requires-Dist: nibabel; extra == 'medical'
Provides-Extra: plot
Requires-Dist: matplotlib>=1.5.3; extra == 'plot'
Provides-Extra: style
Requires-Dist: pre-commit; extra == 'style'
Requires-Dist: ruff; extra == 'style'
Provides-Extra: test
Requires-Dist: coverage; extra == 'test'
Requires-Dist: pytest!=5.3.4; extra == 'test'
Requires-Dist: pytest-cov; extra == 'test'
Requires-Dist: pytest-doctestplus; extra == 'test'
Provides-Extra: typing
Requires-Dist: data-science-types; extra == 'typing'
Requires-Dist: mypy; extra == 'typing'
Requires-Dist: types-pillow; extra == 'typing'
